Metadata-Version: 2.1
Name: todayhitokoto
Version: 0.0.1
Summary: 今日所想，一言，即可概括。
Author-email: Zhihan <zhihan2727@hotmail.com>
License: MIT License
Project-URL: Homepage, https://todayhitokoto.github.io/
Project-URL: Documentation, https://todayhitokoto.github.io/
Project-URL: Repository, https://github.com/TodayHitokoto/api.git
Project-URL: Bug Tracker, https://github.com/TodayHitokoto/api/issues
Keywords: todayhitokoto,hitokoto,api
Requires-Python: >=3.8
License-File: LICENSE
